biofkit/__init__.py
biofkit/proteinKit/__init__.py
biofkit/proteinKit/oldProtein.py
biofkit/proteinKit/pdbKit.py
biofkit/proteinKit/proteinClass.py
biofkit/seqKit/__init__.py
biofkit/seqKit/convKit.py
biofkit/seqKit/cmd/pairwiseDnaAlign.py
biofkit/seqKit/cmd/readFasta.py
biofkit-0.1.18.dist-info/LICENSE
biofkit-0.1.18.dist-info/METADATA
biofkit-0.1.18.dist-info/WHEEL
biofkit-0.1.18.dist-info/entry_points.txt
biofkit-0.1.18.dist-info/top_level.txt
biofkit-0.1.18.dist-info/RECORD
