Metadata-Version: 2.1
Name: biofkit
Version: 0.1.18
Summary: With biofkit you can deal with pdb file (extract sequence, atom information and so on) very easily. Pairwise alignment function is now online.
Author-email: Zhang Yujian <Chouuken@outlook.com>, Wu Yuexin <wuyvexiaoxin@163.com>
Project-URL: Homepage, https://github.com/Chou-Uken/biofkit
Project-URL: Issues, https://github.com/Chou-Uken/biofkit/issues
Classifier: Development Status :: 3 - Alpha
Classifier: Programming Language :: Python :: 3
Classifier: License :: OSI Approved :: Apache Software License
Classifier: Operating System :: OS Independent
Requires-Python: >=3.10
License-File: LICENSE
